surun_tools/.gitignore
surun_tools/__main__.py
surun_tools/build.py
surun_tools/clean.py
surun_tools/clean_vcproj.ipynb
surun_tools/cleanup_build.ipynb
surun_tools/gen_lsp_tdm.py
surun_tools/glob1.py
surun_tools/insert_goignore.py
surun_tools/install.exe
surun_tools/install.py
surun_tools/main.py
surun_tools/merge_cc.py
surun_tools/pipe_client.py
surun_tools/pipe_server.py
surun_tools/run_format.py
soda_surun-2025.5.10.12.dist-info/METADATA
soda_surun-2025.5.10.12.dist-info/WHEEL
soda_surun-2025.5.10.12.dist-info/entry_points.txt
soda_surun-2025.5.10.12.dist-info/RECORD
