Metadata-Version: 2.4
Name: soda-surun
Version: 2025.5.10.12
Summary: surun and related tools
Project-URL: Repository, https://github.com/soda92/surun
Requires-Python: >=3.11
Requires-Dist: sodatools>=2025.2.16.0
